clearedge/__init__.py
clearedge/bbox.py
clearedge/chunk.py
clearedge/dockerfile
clearedge/metadata.py
clearedge/ocr_config/config.yaml
clearedge/reader/__init__.py
clearedge/reader/en_PP-OCRv4_rec_infer.onnx
clearedge/reader/pdf.py
clearedge/utils/__init__.py
clearedge/utils/hf_utils.py
clearedge/utils/pdf_utils.py
clearedge/utils/ultralytics_utils.py
clearedge-0.1.17.dist-info/LICENSE
clearedge-0.1.17.dist-info/METADATA
clearedge-0.1.17.dist-info/WHEEL
clearedge-0.1.17.dist-info/entry_points.txt
clearedge-0.1.17.dist-info/RECORD
