Metadata-Version: 2.1
Name: clearedge
Version: 0.1.17
Summary: 
Author: Clearedge
Requires-Python: >=3.8,<3.12
Classifier: Programming Language :: Python :: 3
Classifier: Programming Language :: Python :: 3.8
Classifier: Programming Language :: Python :: 3.9
Classifier: Programming Language :: Python :: 3.10
Classifier: Programming Language :: Python :: 3.11
Requires-Dist: huggingface-hub (>=0.22.0,<0.23.0)
Requires-Dist: pdf2image (>=1.17.0,<2.0.0)
Requires-Dist: pymupdf (>=1.24.0,<2.0.0)
Requires-Dist: pytesseract (>=0.3.10,<0.4.0)
Requires-Dist: rapid-table (>=0.1.3,<0.2.0)
Requires-Dist: rapidocr-onnxruntime (>=1.3.15,<2.0.0)
Requires-Dist: requests (>=2.31.0,<3.0.0)
Requires-Dist: tf2onnx (>=1.16.1,<2.0.0)
Requires-Dist: tqdm (>=4.66.2,<5.0.0)
Requires-Dist: ultralytics (>=8.0.225,<8.1.0)
Requires-Dist: validators (>=0.22.0,<0.23.0)
